salesforce_id_converter/__init__.py
salesforce_id_converter/cli.py
salesforce_id_converter/converter.py
salesforce_id_converter/utils.py
salesforce_id_converter-0.3.0.dist-info/METADATA
salesforce_id_converter-0.3.0.dist-info/RECORD
salesforce_id_converter-0.3.0.dist-info/WHEEL
salesforce_id_converter-0.3.0.dist-info/entry_points.txt
salesforce_id_converter-0.3.0.dist-info/pbr.json
salesforce_id_converter-0.3.0.dist-info/top_level.txt
