Metadata-Version: 2.1
Name: salesforce-id-converter
Version: 0.3.0
Summary: CLI tool to convert 15 character Salesforce id into a 18 character id
Home-page: https://github.com/amureki/salesforce_id_converter
Author: Rustem Saiargaliev
Author-email: r.sayargaliev@gmail.com
License: Apache-2
Platform: UNKNOWN
Classifier: Development Status :: 4 - Beta
Classifier: Environment :: Console
Classifier: Intended Audience :: Developers
Classifier: License :: OSI Approved :: Apache Software License
Classifier: Operating System :: OS Independent
Classifier: Programming Language :: Python :: 3
